{"_format":"","paths":{"artifacts":"out","build_infos":"out/build-info","sources":"src","tests":"test","scripts":"script","libraries":["lib"]},"files":{"lib/forge-std/src/Base.sol":{"lastModificationDate":1765568557149,"contentHash":"9880db309ccc37a4","interfaceReprHash":null,"sourceName":"lib/forge-std/src/Base.sol","imports":["lib/forge-std/src/StdStorage.sol","lib/forge-std/src/Vm.sol"],"versionRequirement":">=0.6.2, <0.9.0","artifacts":{"CommonBase":{"0.8.30":{"default":{"path":"Base.sol/CommonBase.json","build_id":"f8892e6b4f68fe77"}},"0.8.33":{"default":{"path":"src/Base.sol/CommonBase.json","build_id":"f6f64695d3a6758b"}}},"ScriptBase":{"0.8.30":{"default":{"path":"Base.sol/ScriptBase.json","build_id":"f8892e6b4f68fe77"}},"0.8.33":{"default":{"path":"src/Base.sol/ScriptBase.json","build_id":"f6f64695d3a6758b"}}},"TestBase":{"0.8.30":{"default":{"path":"Base.sol/TestBase.json","build_id":"f8892e6b4f68fe77"}},"0.8.33":{"default":{"path":"src/Base.sol/TestBase.json","build_id":"f6f64695d3a6758b"}}}},"seenByCompiler":true},"lib/forge-std/src/Script.sol":{"lastModificationDate":1765568557150,"contentHash":"f18ee875ff6da793","interfaceReprHash":null,"sourceName":"lib/forge-std/src/Script.sol","imports":["lib/forge-std/src/Base.sol","lib/forge-std/src/StdChains.sol","lib/forge-std/src/StdCheats.sol","lib/forge-std/src/StdConstants.sol","lib/forge-std/src/StdJson.sol","lib/forge-std/src/StdMath.sol","lib/forge-std/src/StdStorage.sol","lib/forge-std/src/StdStyle.sol","lib/forge-std/src/StdUtils.sol","lib/forge-std/src/Vm.sol","lib/forge-std/src/console.sol","lib/forge-std/src/console2.sol","lib/forge-std/src/interfaces/IMulticall3.sol","lib/forge-std/src/safeconsole.sol"],"versionRequirement":">=0.6.2, <0.9.0","artifacts":{"Script":{"0.8.30":{"default":{"path":"Script.sol/Script.json","build_id":"f8892e6b4f68fe77"}},"0.8.33":{"default":{"path":"src/Script.sol/Script.json","build_id":"f6f64695d3a6758b"}}}},"seenByCompiler":true},"lib/forge-std/src/StdChains.sol":{"lastModificationDate":1765568557150,"contentHash":"15a1a266c5880512","interfaceReprHash":null,"sourceName":"lib/forge-std/src/StdChains.sol","imports":["lib/forge-std/src/Vm.sol"],"versionRequirement":">=0.6.2, <0.9.0","artifacts":{"StdChains":{"0.8.30":{"default":{"path":"StdChains.sol/StdChains.json","build_id":"f8892e6b4f68fe77"}},"0.8.33":{"default":{"path":"src/StdChains.sol/StdChains.json","build_id":"f6f64695d3a6758b"}}}},"seenByCompiler":true},"lib/forge-std/src/StdCheats.sol":{"lastModificationDate":1765568557150,"contentHash":"f0dbd553b5869e5a","interfaceReprHash":null,"sourceName":"lib/forge-std/src/StdCheats.sol","imports":["lib/forge-std/src/StdStorage.sol","lib/forge-std/src/Vm.sol","lib/forge-std/src/console.sol","lib/forge-std/src/console2.sol"],"versionRequirement":">=0.6.2, <0.9.0","artifacts":{"StdCheats":{"0.8.30":{"default":{"path":"StdCheats.sol/StdCheats.json","build_id":"f8892e6b4f68fe77"}},"0.8.33":{"default":{"path":"src/StdCheats.sol/StdCheats.json","build_id":"f6f64695d3a6758b"}}},"StdCheatsSafe":{"0.8.30":{"default":{"path":"StdCheats.sol/StdCheatsSafe.json","build_id":"f8892e6b4f68fe77"}},"0.8.33":{"default":{"path":"src/StdCheats.sol/StdCheatsSafe.json","build_id":"f6f64695d3a6758b"}}}},"seenByCompiler":true},"lib/forge-std/src/StdConstants.sol":{"lastModificationDate":1765568557150,"contentHash":"83211db7732fa9bc","interfaceReprHash":null,"sourceName":"lib/forge-std/src/StdConstants.sol","imports":["lib/forge-std/src/Vm.sol","lib/forge-std/src/interfaces/IMulticall3.sol"],"versionRequirement":">=0.6.2, <0.9.0","artifacts":{"StdConstants":{"0.8.30":{"default":{"path":"StdConstants.sol/StdConstants.json","build_id":"f8892e6b4f68fe77"}},"0.8.33":{"default":{"path":"src/StdConstants.sol/StdConstants.json","build_id":"f6f64695d3a6758b"}}}},"seenByCompiler":true},"lib/forge-std/src/StdJson.sol":{"lastModificationDate":1765568557150,"contentHash":"fa627b76988efab7","interfaceReprHash":null,"sourceName":"lib/forge-std/src/StdJson.sol","imports":["lib/forge-std/src/Vm.sol"],"versionRequirement":">=0.6.0, <0.9.0","artifacts":{"stdJson":{"0.8.30":{"default":{"path":"StdJson.sol/stdJson.json","build_id":"f8892e6b4f68fe77"}},"0.8.33":{"default":{"path":"src/StdJson.sol/stdJson.json","build_id":"f6f64695d3a6758b"}}}},"seenByCompiler":true},"lib/forge-std/src/StdMath.sol":{"lastModificationDate":1765568557150,"contentHash":"35a42e2ea32e8a19","interfaceReprHash":null,"sourceName":"lib/forge-std/src/StdMath.sol","imports":[],"versionRequirement":">=0.6.2, <0.9.0","artifacts":{"stdMath":{"0.8.30":{"default":{"path":"StdMath.sol/stdMath.json","build_id":"f8892e6b4f68fe77"}},"0.8.33":{"default":{"path":"src/StdMath.sol/stdMath.json","build_id":"f6f64695d3a6758b"}}}},"seenByCompiler":true},"lib/forge-std/src/StdStorage.sol":{"lastModificationDate":1765568557150,"contentHash":"eed8a0ca870f4f5a","interfaceReprHash":null,"sourceName":"lib/forge-std/src/StdStorage.sol","imports":["lib/forge-std/src/Vm.sol"],"versionRequirement":">=0.6.2, <0.9.0","artifacts":{"stdStorage":{"0.8.30":{"default":{"path":"StdStorage.sol/stdStorage.json","build_id":"f8892e6b4f68fe77"}},"0.8.33":{"default":{"path":"src/StdStorage.sol/stdStorage.json","build_id":"f6f64695d3a6758b"}}},"stdStorageSafe":{"0.8.30":{"default":{"path":"StdStorage.sol/stdStorageSafe.json","build_id":"f8892e6b4f68fe77"}},"0.8.33":{"default":{"path":"src/StdStorage.sol/stdStorageSafe.json","build_id":"f6f64695d3a6758b"}}}},"seenByCompiler":true},"lib/forge-std/src/StdStyle.sol":{"lastModificationDate":1765568557150,"contentHash":"c36f8b31348e8572","interfaceReprHash":null,"sourceName":"lib/forge-std/src/StdStyle.sol","imports":["lib/forge-std/src/Vm.sol"],"versionRequirement":">=0.4.22, <0.9.0","artifacts":{"StdStyle":{"0.8.30":{"default":{"path":"StdStyle.sol/StdStyle.json","build_id":"f8892e6b4f68fe77"}},"0.8.33":{"default":{"path":"src/StdStyle.sol/StdStyle.json","build_id":"f6f64695d3a6758b"}}}},"seenByCompiler":true},"lib/forge-std/src/StdUtils.sol":{"lastModificationDate":1765568557150,"contentHash":"1220ac036ff4a4b2","interfaceReprHash":null,"sourceName":"lib/forge-std/src/StdUtils.sol","imports":["lib/forge-std/src/Vm.sol","lib/forge-std/src/interfaces/IMulticall3.sol"],"versionRequirement":">=0.6.2, <0.9.0","artifacts":{"StdUtils":{"0.8.30":{"default":{"path":"StdUtils.sol/StdUtils.json","build_id":"f8892e6b4f68fe77"}},"0.8.33":{"default":{"path":"src/StdUtils.sol/StdUtils.json","build_id":"f6f64695d3a6758b"}}}},"seenByCompiler":true},"lib/forge-std/src/Vm.sol":{"lastModificationDate":1765568557150,"contentHash":"00c7599a02739501","interfaceReprHash":null,"sourceName":"lib/forge-std/src/Vm.sol","imports":[],"versionRequirement":">=0.6.2, <0.9.0","artifacts":{"Vm":{"0.8.30":{"default":{"path":"Vm.sol/Vm.json","build_id":"f8892e6b4f68fe77"}},"0.8.33":{"default":{"path":"src/Vm.sol/Vm.json","build_id":"f6f64695d3a6758b"}}},"VmSafe":{"0.8.30":{"default":{"path":"Vm.sol/VmSafe.json","build_id":"f8892e6b4f68fe77"}},"0.8.33":{"default":{"path":"src/Vm.sol/VmSafe.json","build_id":"f6f64695d3a6758b"}}}},"seenByCompiler":true},"lib/forge-std/src/console.sol":{"lastModificationDate":1765568557151,"contentHash":"d066adc60d3a1a8f","interfaceReprHash":null,"sourceName":"lib/forge-std/src/console.sol","imports":[],"versionRequirement":">=0.4.22, <0.9.0","artifacts":{"console":{"0.8.30":{"default":{"path":"console.sol/console.json","build_id":"f8892e6b4f68fe77"}},"0.8.33":{"default":{"path":"src/console.sol/console.json","build_id":"f6f64695d3a6758b"}}}},"seenByCompiler":true},"lib/forge-std/src/console2.sol":{"lastModificationDate":1765568557151,"contentHash":"339df1727370a5a3","interfaceReprHash":null,"sourceName":"lib/forge-std/src/console2.sol","imports":["lib/forge-std/src/console.sol"],"versionRequirement":">=0.4.22, <0.9.0","artifacts":{},"seenByCompiler":true},"lib/forge-std/src/interfaces/IMulticall3.sol":{"lastModificationDate":1765568557151,"contentHash":"1d7fd847a2861d72","interfaceReprHash":null,"sourceName":"lib/forge-std/src/interfaces/IMulticall3.sol","imports":[],"versionRequirement":">=0.6.2, <0.9.0","artifacts":{"IMulticall3":{"0.8.30":{"default":{"path":"IMulticall3.sol/IMulticall3.json","build_id":"f8892e6b4f68fe77"}},"0.8.33":{"default":{"path":"interfaces/IMulticall3.sol/IMulticall3.json","build_id":"f6f64695d3a6758b"}}}},"seenByCompiler":true},"lib/forge-std/src/safeconsole.sol":{"lastModificationDate":1765568557152,"contentHash":"a253b907b4c1dc54","interfaceReprHash":null,"sourceName":"lib/forge-std/src/safeconsole.sol","imports":[],"versionRequirement":">=0.6.2, <0.9.0","artifacts":{"safeconsole":{"0.8.30":{"default":{"path":"safeconsole.sol/safeconsole.json","build_id":"f8892e6b4f68fe77"}},"0.8.33":{"default":{"path":"src/safeconsole.sol/safeconsole.json","build_id":"f6f64695d3a6758b"}}}},"seenByCompiler":true},"script/QuadVoting.s.sol":{"lastModificationDate":1766745911508,"contentHash":"86c1b53d51306ea1","interfaceReprHash":null,"sourceName":"script/QuadVoting.s.sol","imports":["lib/forge-std/src/Base.sol","lib/forge-std/src/Script.sol","lib/forge-std/src/StdChains.sol","lib/forge-std/src/StdCheats.sol","lib/forge-std/src/StdConstants.sol","lib/forge-std/src/StdJson.sol","lib/forge-std/src/StdMath.sol","lib/forge-std/src/StdStorage.sol","lib/forge-std/src/StdStyle.sol","lib/forge-std/src/StdUtils.sol","lib/forge-std/src/Vm.sol","lib/forge-std/src/console.sol","lib/forge-std/src/console2.sol","lib/forge-std/src/interfaces/IMulticall3.sol","lib/forge-std/src/safeconsole.sol","src/QuadVoting.sol"],"versionRequirement":">=0.8.2, <0.9.0","artifacts":{"CastVote":{"0.8.30":{"default":{"path":"QuadVoting.s.sol/CastVote.json","build_id":"80afd41520471759"}}},"CheckResults":{"0.8.30":{"default":{"path":"QuadVoting.s.sol/CheckResults.json","build_id":"80afd41520471759"}}},"DeployQuadVoting":{"0.8.30":{"default":{"path":"QuadVoting.s.sol/DeployQuadVoting.json","build_id":"80afd41520471759"}}},"FullDeployment":{"0.8.30":{"default":{"path":"QuadVoting.s.sol/FullDeployment.json","build_id":"80afd41520471759"}}},"SetupVoters":{"0.8.30":{"default":{"path":"QuadVoting.s.sol/SetupVoters.json","build_id":"80afd41520471759"}}}},"seenByCompiler":true},"src/QuadVoting.sol":{"lastModificationDate":1766495939052,"contentHash":"8dc7b6540183ca25","interfaceReprHash":null,"sourceName":"src/QuadVoting.sol","imports":[],"versionRequirement":">=0.8.2, <0.9.0","artifacts":{"QuadVoting":{"0.8.30":{"default":{"path":"QuadVoting.sol/QuadVoting.json","build_id":"af58b61eeea03f19"}}}},"seenByCompiler":true}},"builds":["80afd41520471759","af58b61eeea03f19","f6f64695d3a6758b","f8892e6b4f68fe77"],"profiles":{"default":{"solc":{"optimizer":{"enabled":false,"runs":200},"metadata":{"useLiteralContent":false,"bytecodeHash":"ipfs","appendCBOR":true},"outputSelection":{"*":{"*":["abi","evm.bytecode.object","evm.bytecode.sourceMap","evm.bytecode.linkReferences","evm.deployedBytecode.object","evm.deployedBytecode.sourceMap","evm.deployedBytecode.linkReferences","evm.deployedBytecode.immutableReferences","evm.methodIdentifiers","metadata"]}},"evmVersion":"prague","viaIR":false,"libraries":{}},"vyper":{"evmVersion":"prague","outputSelection":{"*":{"*":["abi","evm.bytecode","evm.deployedBytecode"]}}}}},"preprocessed":false,"mocks":[]}